django_deprecate_fields/__init__.py
django_deprecate_fields/deprecate_field.py
django_deprecate_fields-0.2.3.dist-info/licenses/LICENSE
django_deprecate_fields-0.2.3.dist-info/METADATA
django_deprecate_fields-0.2.3.dist-info/WHEEL
django_deprecate_fields-0.2.3.dist-info/top_level.txt
django_deprecate_fields-0.2.3.dist-info/RECORD
